[
  {
    "ContainingType": "JucieAndFlower.Controllers.AuthController",
    "Method": "Login",
    "RelativePath": "api/Auth/login",
    "HttpMethod": "POST",
    "IsController": true,
    "Order": 0,
    "Parameters": [
      {
        "Name": "request",
        "Type": "JucieAndFlower.Data.Enities.Login.LoginRequest",
        "IsRequired": true
      }
    ],
    "ReturnTypes": []
  },
  {
    "ContainingType": "JucieAndFlower.Controllers.AuthController",
    "Method": "Logout",
    "RelativePath": "api/Auth/logout",
    "HttpMethod": "POST",
    "IsController": true,
    "Order": 0,
    "Parameters": [],
    "ReturnTypes": []
  },
  {
    "ContainingType": "JucieAndFlower.Controllers.AuthController",
    "Method": "GetProfile",
    "RelativePath": "api/Auth/profile",
    "HttpMethod": "GET",
    "IsController": true,
    "Order": 0,
    "Parameters": [],
    "ReturnTypes": []
  },
  {
    "ContainingType": "JucieAndFlower.Controllers.AuthController",
    "Method": "Refresh",
    "RelativePath": "api/Auth/refresh-token",
    "HttpMethod": "POST",
    "IsController": true,
    "Order": 0,
    "Parameters": [
      {
        "Name": "model",
        "Type": "JucieAndFlower.Data.Enities.Login.TokenModel",
        "IsRequired": true
      }
    ],
    "ReturnTypes": []
  },
  {
    "ContainingType": "JucieAndFlower.Controllers.AuthController",
    "Method": "Register",
    "RelativePath": "api/Auth/register",
    "HttpMethod": "POST",
    "IsController": true,
    "Order": 0,
    "Parameters": [
      {
        "Name": "dto",
        "Type": "JucieAndFlower.Data.Enities.User.UserRegisterDto",
        "IsRequired": true
      }
    ],
    "ReturnTypes": []
  },
  {
    "ContainingType": "JucieAndFlower.Controllers.AuthController",
    "Method": "UpdateProfile",
    "RelativePath": "api/Auth/update-profile",
    "HttpMethod": "PUT",
    "IsController": true,
    "Order": 0,
    "Parameters": [
      {
        "Name": "dto",
        "Type": "JucieAndFlower.Data.Enities.User.UserUpdateDto",
        "IsRequired": true
      }
    ],
    "ReturnTypes": []
  },
  {
    "ContainingType": "JucieAndFlower.Controllers.AuthController",
    "Method": "VerifyEmail",
    "RelativePath": "api/Auth/verify-email",
    "HttpMethod": "GET",
    "IsController": true,
    "Order": 0,
    "Parameters": [
      {
        "Name": "email",
        "Type": "System.String",
        "IsRequired": false
      },
      {
        "Name": "token",
        "Type": "System.String",
        "IsRequired": false
      }
    ],
    "ReturnTypes": []
  },
  {
    "ContainingType": "JucieAndFlower.Controllers.CartController",
    "Method": "GetCart",
    "RelativePath": "api/Cart",
    "HttpMethod": "GET",
    "IsController": true,
    "Order": 0,
    "Parameters": [],
    "ReturnTypes": []
  },
  {
    "ContainingType": "JucieAndFlower.Controllers.CartController",
    "Method": "AddOrUpdateCartItem",
    "RelativePath": "api/Cart",
    "HttpMethod": "POST",
    "IsController": true,
    "Order": 0,
    "Parameters": [
      {
        "Name": "dto",
        "Type": "JucieAndFlower.Data.Enities.Cart.CartItemCreateDTO",
        "IsRequired": true
      }
    ],
    "ReturnTypes": []
  },
  {
    "ContainingType": "JucieAndFlower.Controllers.CartController",
    "Method": "DeleteItem",
    "RelativePath": "api/Cart/{productId}",
    "HttpMethod": "DELETE",
    "IsController": true,
    "Order": 0,
    "Parameters": [
      {
        "Name": "productId",
        "Type": "System.Int32",
        "IsRequired": true
      }
    ],
    "ReturnTypes": []
  },
  {
    "ContainingType": "JucieAndFlower.Controllers.CartController",
    "Method": "AddCustomItem",
    "RelativePath": "api/Cart/custom",
    "HttpMethod": "POST",
    "IsController": true,
    "Order": 0,
    "Parameters": [
      {
        "Name": "dto",
        "Type": "JucieAndFlower.Data.Enities.Cart.CustomCartItemCreateDTO",
        "IsRequired": true
      }
    ],
    "ReturnTypes": []
  },
  {
    "ContainingType": "JucieAndFlower.Controllers.CategoryController",
    "Method": "GetAll",
    "RelativePath": "api/Category",
    "HttpMethod": "GET",
    "IsController": true,
    "Order": 0,
    "Parameters": [],
    "ReturnTypes": []
  },
  {
    "ContainingType": "JucieAndFlower.Controllers.CategoryController",
    "Method": "Create",
    "RelativePath": "api/Category",
    "HttpMethod": "POST",
    "IsController": true,
    "Order": 0,
    "Parameters": [
      {
        "Name": "dto",
        "Type": "JucieAndFlower.Data.Enities.Categories.CategoryNoID",
        "IsRequired": true
      }
    ],
    "ReturnTypes": []
  },
  {
    "ContainingType": "JucieAndFlower.Controllers.CategoryController",
    "Method": "Get",
    "RelativePath": "api/Category/{id}",
    "HttpMethod": "GET",
    "IsController": true,
    "Order": 0,
    "Parameters": [
      {
        "Name": "id",
        "Type": "System.Int32",
        "IsRequired": true
      }
    ],
    "ReturnTypes": []
  },
  {
    "ContainingType": "JucieAndFlower.Controllers.CategoryController",
    "Method": "Update",
    "RelativePath": "api/Category/{id}",
    "HttpMethod": "PUT",
    "IsController": true,
    "Order": 0,
    "Parameters": [
      {
        "Name": "id",
        "Type": "System.Int32",
        "IsRequired": true
      },
      {
        "Name": "dto",
        "Type": "JucieAndFlower.Data.Enities.Categories.CategoryNoID",
        "IsRequired": true
      }
    ],
    "ReturnTypes": []
  },
  {
    "ContainingType": "JucieAndFlower.Controllers.CategoryController",
    "Method": "Delete",
    "RelativePath": "api/Category/{id}",
    "HttpMethod": "DELETE",
    "IsController": true,
    "Order": 0,
    "Parameters": [
      {
        "Name": "id",
        "Type": "System.Int32",
        "IsRequired": true
      }
    ],
    "ReturnTypes": []
  },
  {
    "ContainingType": "JucieAndFlower.Controllers.CustomFlowerItemController",
    "Method": "CreateCustomItem",
    "RelativePath": "api/CustomFlowerItem",
    "HttpMethod": "POST",
    "IsController": true,
    "Order": 0,
    "Parameters": [
      {
        "Name": "dto",
        "Type": "JucieAndFlower.Data.Enities.CusFlower.CustomFlowerItemCreateDTO",
        "IsRequired": true
      }
    ],
    "ReturnTypes": []
  },
  {
    "ContainingType": "JucieAndFlower.Controllers.CustomFlowerItemController",
    "Method": "GetUserCustomItems",
    "RelativePath": "api/CustomFlowerItem",
    "HttpMethod": "GET",
    "IsController": true,
    "Order": 0,
    "Parameters": [],
    "ReturnTypes": []
  },
  {
    "ContainingType": "JucieAndFlower.Controllers.FeedbackController",
    "Method": "GetAll",
    "RelativePath": "api/Feedback",
    "HttpMethod": "GET",
    "IsController": true,
    "Order": 0,
    "Parameters": [],
    "ReturnTypes": []
  },
  {
    "ContainingType": "JucieAndFlower.Controllers.FeedbackController",
    "Method": "Create",
    "RelativePath": "api/Feedback",
    "HttpMethod": "POST",
    "IsController": true,
    "Order": 0,
    "Parameters": [
      {
        "Name": "dto",
        "Type": "JucieAndFlower.Data.Enities.Feedback.FeedbackCreateDto",
        "IsRequired": true
      }
    ],
    "ReturnTypes": []
  },
  {
    "ContainingType": "JucieAndFlower.Controllers.FeedbackController",
    "Method": "GetById",
    "RelativePath": "api/Feedback/{id}",
    "HttpMethod": "GET",
    "IsController": true,
    "Order": 0,
    "Parameters": [
      {
        "Name": "id",
        "Type": "System.Int32",
        "IsRequired": true
      }
    ],
    "ReturnTypes": []
  },
  {
    "ContainingType": "JucieAndFlower.Controllers.FeedbackController",
    "Method": "Update",
    "RelativePath": "api/Feedback/{id}",
    "HttpMethod": "PUT",
    "IsController": true,
    "Order": 0,
    "Parameters": [
      {
        "Name": "id",
        "Type": "System.Int32",
        "IsRequired": true
      },
      {
        "Name": "dto",
        "Type": "JucieAndFlower.Data.Enities.Feedback.FeedbackUpdateDto",
        "IsRequired": true
      }
    ],
    "ReturnTypes": []
  },
  {
    "ContainingType": "JucieAndFlower.Controllers.FeedbackController",
    "Method": "Delete",
    "RelativePath": "api/Feedback/{id}",
    "HttpMethod": "DELETE",
    "IsController": true,
    "Order": 0,
    "Parameters": [
      {
        "Name": "id",
        "Type": "System.Int32",
        "IsRequired": true
      }
    ],
    "ReturnTypes": []
  },
  {
    "ContainingType": "JucieAndFlower.Controllers.FlowerComponentsController",
    "Method": "GetAll",
    "RelativePath": "api/FlowerComponents",
    "HttpMethod": "GET",
    "IsController": true,
    "Order": 0,
    "Parameters": [],
    "ReturnTypes": []
  },
  {
    "ContainingType": "JucieAndFlower.Controllers.FlowerComponentsController",
    "Method": "Create",
    "RelativePath": "api/FlowerComponents",
    "HttpMethod": "POST",
    "IsController": true,
    "Order": 0,
    "Parameters": [
      {
        "Name": "dto",
        "Type": "JucieAndFlower.Data.Enities.CusFlower.FlowerComponentDto",
        "IsRequired": true
      }
    ],
    "ReturnTypes": []
  },
  {
    "ContainingType": "JucieAndFlower.Controllers.FlowerComponentsController",
    "Method": "GetById",
    "RelativePath": "api/FlowerComponents/{id}",
    "HttpMethod": "GET",
    "IsController": true,
    "Order": 0,
    "Parameters": [
      {
        "Name": "id",
        "Type": "System.Int32",
        "IsRequired": true
      }
    ],
    "ReturnTypes": []
  },
  {
    "ContainingType": "JucieAndFlower.Controllers.FlowerComponentsController",
    "Method": "Update",
    "RelativePath": "api/FlowerComponents/{id}",
    "HttpMethod": "PUT",
    "IsController": true,
    "Order": 0,
    "Parameters": [
      {
        "Name": "id",
        "Type": "System.Int32",
        "IsRequired": true
      },
      {
        "Name": "dto",
        "Type": "JucieAndFlower.Data.Enities.CusFlower.FlowerComponentDto",
        "IsRequired": true
      }
    ],
    "ReturnTypes": []
  },
  {
    "ContainingType": "JucieAndFlower.Controllers.FlowerComponentsController",
    "Method": "Delete",
    "RelativePath": "api/FlowerComponents/{id}",
    "HttpMethod": "DELETE",
    "IsController": true,
    "Order": 0,
    "Parameters": [
      {
        "Name": "id",
        "Type": "System.Int32",
        "IsRequired": true
      }
    ],
    "ReturnTypes": []
  },
  {
    "ContainingType": "JucieAndFlower.Controllers.OrdersController",
    "Method": "GetOrderById",
    "RelativePath": "api/Orders",
    "HttpMethod": "GET",
    "IsController": true,
    "Order": 0,
    "Parameters": [
      {
        "Name": "id",
        "Type": "System.Int32",
        "IsRequired": false
      }
    ],
    "ReturnTypes": []
  },
  {
    "ContainingType": "JucieAndFlower.Controllers.OrdersController",
    "Method": "CreateOrderFromCart",
    "RelativePath": "api/Orders/from-cart",
    "HttpMethod": "POST",
    "IsController": true,
    "Order": 0,
    "Parameters": [
      {
        "Name": "dto",
        "Type": "JucieAndFlower.Data.Enities.Order.OrderFromCartDTO",
        "IsRequired": true
      }
    ],
    "ReturnTypes": []
  },
  {
    "ContainingType": "JucieAndFlower.Controllers.OrdersController",
    "Method": "PaymentReturn",
    "RelativePath": "api/Orders/payment-return",
    "HttpMethod": "GET",
    "IsController": true,
    "Order": 0,
    "Parameters": [],
    "ReturnTypes": []
  },
  {
    "ContainingType": "JucieAndFlower.Controllers.OrdersController",
    "Method": "GetUserOrders",
    "RelativePath": "api/Orders/user",
    "HttpMethod": "GET",
    "IsController": true,
    "Order": 0,
    "Parameters": [],
    "ReturnTypes": []
  },
  {
    "ContainingType": "JucieAndFlower.Controllers.PaymentController",
    "Method": "GetPayments",
    "RelativePath": "api/Payment",
    "HttpMethod": "GET",
    "IsController": true,
    "Order": 0,
    "Parameters": [],
    "ReturnTypes": []
  },
  {
    "ContainingType": "JucieAndFlower.Controllers.ProductDetailController",
    "Method": "GetAll",
    "RelativePath": "api/ProductDetail",
    "HttpMethod": "GET",
    "IsController": true,
    "Order": 0,
    "Parameters": [],
    "ReturnTypes": []
  },
  {
    "ContainingType": "JucieAndFlower.Controllers.ProductDetailController",
    "Method": "Create",
    "RelativePath": "api/ProductDetail",
    "HttpMethod": "POST",
    "IsController": true,
    "Order": 0,
    "Parameters": [
      {
        "Name": "dto",
        "Type": "JucieAndFlower.Data.Enities.ProductDetails.ProductDetailCreateDTO",
        "IsRequired": true
      }
    ],
    "ReturnTypes": []
  },
  {
    "ContainingType": "JucieAndFlower.Controllers.ProductDetailController",
    "Method": "GetById",
    "RelativePath": "api/ProductDetail/{id}",
    "HttpMethod": "GET",
    "IsController": true,
    "Order": 0,
    "Parameters": [
      {
        "Name": "id",
        "Type": "System.Int32",
        "IsRequired": true
      }
    ],
    "ReturnTypes": []
  },
  {
    "ContainingType": "JucieAndFlower.Controllers.ProductDetailController",
    "Method": "Update",
    "RelativePath": "api/ProductDetail/{id}",
    "HttpMethod": "PUT",
    "IsController": true,
    "Order": 0,
    "Parameters": [
      {
        "Name": "id",
        "Type": "System.Int32",
        "IsRequired": true
      },
      {
        "Name": "dto",
        "Type": "JucieAndFlower.Data.Enities.ProductDetails.ProductDetailCreateDTO",
        "IsRequired": true
      }
    ],
    "ReturnTypes": []
  },
  {
    "ContainingType": "JucieAndFlower.Controllers.ProductDetailController",
    "Method": "Delete",
    "RelativePath": "api/ProductDetail/{id}",
    "HttpMethod": "DELETE",
    "IsController": true,
    "Order": 0,
    "Parameters": [
      {
        "Name": "id",
        "Type": "System.Int32",
        "IsRequired": true
      }
    ],
    "ReturnTypes": []
  },
  {
    "ContainingType": "JucieAndFlower.Controllers.ProductsController",
    "Method": "GetAll",
    "RelativePath": "api/Products",
    "HttpMethod": "GET",
    "IsController": true,
    "Order": 0,
    "Parameters": [],
    "ReturnTypes": []
  },
  {
    "ContainingType": "JucieAndFlower.Controllers.ProductsController",
    "Method": "Create",
    "RelativePath": "api/Products",
    "HttpMethod": "POST",
    "IsController": true,
    "Order": 0,
    "Parameters": [
      {
        "Name": "product",
        "Type": "JucieAndFlower.Data.Enities.Product.ProductCreateUpdateDto",
        "IsRequired": true
      }
    ],
    "ReturnTypes": []
  },
  {
    "ContainingType": "JucieAndFlower.Controllers.ProductsController",
    "Method": "GetById",
    "RelativePath": "api/Products/{id}",
    "HttpMethod": "GET",
    "IsController": true,
    "Order": 0,
    "Parameters": [
      {
        "Name": "id",
        "Type": "System.Int32",
        "IsRequired": true
      }
    ],
    "ReturnTypes": []
  },
  {
    "ContainingType": "JucieAndFlower.Controllers.ProductsController",
    "Method": "Update",
    "RelativePath": "api/Products/{id}",
    "HttpMethod": "PUT",
    "IsController": true,
    "Order": 0,
    "Parameters": [
      {
        "Name": "id",
        "Type": "System.Int32",
        "IsRequired": true
      },
      {
        "Name": "product",
        "Type": "JucieAndFlower.Data.Enities.Product.ProductCreateUpdateDto",
        "IsRequired": true
      }
    ],
    "ReturnTypes": []
  },
  {
    "ContainingType": "JucieAndFlower.Controllers.ProductsController",
    "Method": "Delete",
    "RelativePath": "api/Products/{id}",
    "HttpMethod": "DELETE",
    "IsController": true,
    "Order": 0,
    "Parameters": [
      {
        "Name": "id",
        "Type": "System.Int32",
        "IsRequired": true
      }
    ],
    "ReturnTypes": []
  },
  {
    "ContainingType": "JucieAndFlower.Controllers.ProductsController",
    "Method": "UploadImage",
    "RelativePath": "api/Products/{productId}/images",
    "HttpMethod": "POST",
    "IsController": true,
    "Order": 0,
    "Parameters": [
      {
        "Name": "productId",
        "Type": "System.Int32",
        "IsRequired": true
      },
      {
        "Name": "file",
        "Type": "Microsoft.AspNetCore.Http.IFormFile",
        "IsRequired": false
      }
    ],
    "ReturnTypes": []
  },
  {
    "ContainingType": "JucieAndFlower.Controllers.ProductsController",
    "Method": "GetByCategoryId",
    "RelativePath": "api/Products/categoryId",
    "HttpMethod": "GET",
    "IsController": true,
    "Order": 0,
    "Parameters": [
      {
        "Name": "categoryId",
        "Type": "System.Int32",
        "IsRequired": false
      }
    ],
    "ReturnTypes": []
  },
  {
    "ContainingType": "JucieAndFlower.Controllers.PromotionController",
    "Method": "GetAll",
    "RelativePath": "api/Promotion",
    "HttpMethod": "GET",
    "IsController": true,
    "Order": 0,
    "Parameters": [],
    "ReturnTypes": []
  },
  {
    "ContainingType": "JucieAndFlower.Controllers.PromotionController",
    "Method": "Create",
    "RelativePath": "api/Promotion",
    "HttpMethod": "POST",
    "IsController": true,
    "Order": 0,
    "Parameters": [
      {
        "Name": "dto",
        "Type": "JucieAndFlower.Data.Enities.Promotion.PromotionCreateUpdateDTO",
        "IsRequired": true
      }
    ],
    "ReturnTypes": []
  },
  {
    "ContainingType": "JucieAndFlower.Controllers.PromotionController",
    "Method": "Get",
    "RelativePath": "api/Promotion/{id}",
    "HttpMethod": "GET",
    "IsController": true,
    "Order": 0,
    "Parameters": [
      {
        "Name": "id",
        "Type": "System.Int32",
        "IsRequired": true
      }
    ],
    "ReturnTypes": []
  },
  {
    "ContainingType": "JucieAndFlower.Controllers.PromotionController",
    "Method": "Update",
    "RelativePath": "api/Promotion/{id}",
    "HttpMethod": "PUT",
    "IsController": true,
    "Order": 0,
    "Parameters": [
      {
        "Name": "id",
        "Type": "System.Int32",
        "IsRequired": true
      },
      {
        "Name": "dto",
        "Type": "JucieAndFlower.Data.Enities.Promotion.PromotionCreateUpdateDTO",
        "IsRequired": true
      }
    ],
    "ReturnTypes": []
  },
  {
    "ContainingType": "JucieAndFlower.Controllers.PromotionController",
    "Method": "Delete",
    "RelativePath": "api/Promotion/{id}",
    "HttpMethod": "DELETE",
    "IsController": true,
    "Order": 0,
    "Parameters": [
      {
        "Name": "id",
        "Type": "System.Int32",
        "IsRequired": true
      }
    ],
    "ReturnTypes": []
  },
  {
    "ContainingType": "JucieAndFlower.Controllers.RevenueController",
    "Method": "GetDailyRevenue",
    "RelativePath": "api/Revenue/daily",
    "HttpMethod": "GET",
    "IsController": true,
    "Order": 0,
    "Parameters": [
      {
        "Name": "startDate",
        "Type": "System.Nullable\u00601[[System.DateTime, System.Private.CoreLib, Version=8.0.0.0, Culture=neutral, PublicKeyToken=7cec85d7bea7798e]]",
        "IsRequired": false
      },
      {
        "Name": "endDate",
        "Type": "System.Nullable\u00601[[System.DateTime, System.Private.CoreLib, Version=8.0.0.0, Culture=neutral, PublicKeyToken=7cec85d7bea7798e]]",
        "IsRequired": false
      }
    ],
    "ReturnTypes": []
  },
  {
    "ContainingType": "JucieAndFlower.Controllers.RevenueController",
    "Method": "GetMonthlyRevenue",
    "RelativePath": "api/Revenue/monthly",
    "HttpMethod": "GET",
    "IsController": true,
    "Order": 0,
    "Parameters": [
      {
        "Name": "year",
        "Type": "System.Nullable\u00601[[System.Int32, System.Private.CoreLib, Version=8.0.0.0, Culture=neutral, PublicKeyToken=7cec85d7bea7798e]]",
        "IsRequired": false
      }
    ],
    "ReturnTypes": []
  },
  {
    "ContainingType": "JucieAndFlower.Controllers.RevenueController",
    "Method": "GetOrderStatusStats",
    "RelativePath": "api/Revenue/order-status-stats",
    "HttpMethod": "GET",
    "IsController": true,
    "Order": 0,
    "Parameters": [
      {
        "Name": "startDate",
        "Type": "System.Nullable\u00601[[System.DateTime, System.Private.CoreLib, Version=8.0.0.0, Culture=neutral, PublicKeyToken=7cec85d7bea7798e]]",
        "IsRequired": false
      },
      {
        "Name": "endDate",
        "Type": "System.Nullable\u00601[[System.DateTime, System.Private.CoreLib, Version=8.0.0.0, Culture=neutral, PublicKeyToken=7cec85d7bea7798e]]",
        "IsRequired": false
      }
    ],
    "ReturnTypes": []
  },
  {
    "ContainingType": "JucieAndFlower.Controllers.RevenueController",
    "Method": "GetRevenueStats",
    "RelativePath": "api/Revenue/stats",
    "HttpMethod": "GET",
    "IsController": true,
    "Order": 0,
    "Parameters": [],
    "ReturnTypes": []
  },
  {
    "ContainingType": "JucieAndFlower.Controllers.RevenueController",
    "Method": "GetTopProducts",
    "RelativePath": "api/Revenue/top-products",
    "HttpMethod": "GET",
    "IsController": true,
    "Order": 0,
    "Parameters": [
      {
        "Name": "limit",
        "Type": "System.Int32",
        "IsRequired": false
      },
      {
        "Name": "startDate",
        "Type": "System.Nullable\u00601[[System.DateTime, System.Private.CoreLib, Version=8.0.0.0, Culture=neutral, PublicKeyToken=7cec85d7bea7798e]]",
        "IsRequired": false
      },
      {
        "Name": "endDate",
        "Type": "System.Nullable\u00601[[System.DateTime, System.Private.CoreLib, Version=8.0.0.0, Culture=neutral, PublicKeyToken=7cec85d7bea7798e]]",
        "IsRequired": false
      }
    ],
    "ReturnTypes": []
  },
  {
    "ContainingType": "JucieAndFlower.Controllers.WorkshopController",
    "Method": "GetAll",
    "RelativePath": "api/Workshop",
    "HttpMethod": "GET",
    "IsController": true,
    "Order": 0,
    "Parameters": [],
    "ReturnTypes": []
  },
  {
    "ContainingType": "JucieAndFlower.Controllers.WorkshopController",
    "Method": "Create",
    "RelativePath": "api/Workshop",
    "HttpMethod": "POST",
    "IsController": true,
    "Order": 0,
    "Parameters": [
      {
        "Name": "dto",
        "Type": "JucieAndFlower.Data.Enities.Worshop.WorkshopDTO",
        "IsRequired": true
      }
    ],
    "ReturnTypes": []
  },
  {
    "ContainingType": "JucieAndFlower.Controllers.WorkshopController",
    "Method": "Get",
    "RelativePath": "api/Workshop/{id}",
    "HttpMethod": "GET",
    "IsController": true,
    "Order": 0,
    "Parameters": [
      {
        "Name": "id",
        "Type": "System.Int32",
        "IsRequired": true
      }
    ],
    "ReturnTypes": []
  },
  {
    "ContainingType": "JucieAndFlower.Controllers.WorkshopController",
    "Method": "Update",
    "RelativePath": "api/Workshop/{id}",
    "HttpMethod": "PUT",
    "IsController": true,
    "Order": 0,
    "Parameters": [
      {
        "Name": "id",
        "Type": "System.Int32",
        "IsRequired": true
      },
      {
        "Name": "dto",
        "Type": "JucieAndFlower.Data.Enities.Worshop.WorkshopDTO",
        "IsRequired": true
      }
    ],
    "ReturnTypes": []
  },
  {
    "ContainingType": "JucieAndFlower.Controllers.WorkshopController",
    "Method": "Delete",
    "RelativePath": "api/Workshop/{id}",
    "HttpMethod": "DELETE",
    "IsController": true,
    "Order": 0,
    "Parameters": [
      {
        "Name": "id",
        "Type": "System.Int32",
        "IsRequired": true
      }
    ],
    "ReturnTypes": []
  },
  {
    "ContainingType": "JucieAndFlower.Controllers.WorkshopTicketController",
    "Method": "GetAll",
    "RelativePath": "api/WorkshopTicket",
    "HttpMethod": "GET",
    "IsController": true,
    "Order": 0,
    "Parameters": [],
    "ReturnTypes": []
  },
  {
    "ContainingType": "JucieAndFlower.Controllers.WorkshopTicketController",
    "Method": "Create",
    "RelativePath": "api/WorkshopTicket",
    "HttpMethod": "POST",
    "IsController": true,
    "Order": 0,
    "Parameters": [
      {
        "Name": "dto",
        "Type": "JucieAndFlower.Data.Enities.Worshop.WorkshopTicketDTO",
        "IsRequired": true
      }
    ],
    "ReturnTypes": []
  },
  {
    "ContainingType": "JucieAndFlower.Controllers.WorkshopTicketController",
    "Method": "Get",
    "RelativePath": "api/WorkshopTicket/{id}",
    "HttpMethod": "GET",
    "IsController": true,
    "Order": 0,
    "Parameters": [
      {
        "Name": "id",
        "Type": "System.Int32",
        "IsRequired": true
      }
    ],
    "ReturnTypes": []
  },
  {
    "ContainingType": "JucieAndFlower.Controllers.WorkshopTicketController",
    "Method": "Update",
    "RelativePath": "api/WorkshopTicket/{id}",
    "HttpMethod": "PUT",
    "IsController": true,
    "Order": 0,
    "Parameters": [
      {
        "Name": "id",
        "Type": "System.Int32",
        "IsRequired": true
      },
      {
        "Name": "dto",
        "Type": "JucieAndFlower.Data.Enities.Worshop.WorkshopTicketDTO",
        "IsRequired": true
      }
    ],
    "ReturnTypes": []
  },
  {
    "ContainingType": "JucieAndFlower.Controllers.WorkshopTicketController",
    "Method": "Delete",
    "RelativePath": "api/WorkshopTicket/{id}",
    "HttpMethod": "DELETE",
    "IsController": true,
    "Order": 0,
    "Parameters": [
      {
        "Name": "id",
        "Type": "System.Int32",
        "IsRequired": true
      }
    ],
    "ReturnTypes": []
  }
]